OpenImageIO/OpenImageIO.cpython-39-x86_64-linux-gnu.so
OpenImageIO/__init__.py
PyOpenColorIO/PyOpenColorIO.so
PyOpenColorIO/__init__.py
oiio_static_python.libs/libatomic-35750833.so.1.0.0
oiio_static_python.libs/libtbb-06dd97bf.so.12.10
oiio_static_python.libs/libtbbmalloc-32a11529.so.2.10
oiio_static_python.libs/libtbbmalloc_proxy-2b6fc50f.so.2.10
oiio_static_python-3.0.7.0.1.dist-info/METADATA
oiio_static_python-3.0.7.0.1.dist-info/WHEEL
oiio_static_python-3.0.7.0.1.dist-info/top_level.txt
oiio_static_python-3.0.7.0.1.dist-info/RECORD
oiio_static_python-3.0.7.0.1.dist-info/licenses/LICENSE-GPL
oiio_static_python-3.0.7.0.1.dist-info/licenses/licenses/fmt-LICENSE
oiio_static_python-3.0.7.0.1.dist-info/licenses/licenses/freetype-LICENSE
oiio_static_python-3.0.7.0.1.dist-info/licenses/licenses/giflib-LICENSE
oiio_static_python-3.0.7.0.1.dist-info/licenses/licenses/hdf5-LICENSE
oiio_static_python-3.0.7.0.1.dist-info/licenses/licenses/imath-LICENSE
oiio_static_python-3.0.7.0.1.dist-info/licenses/licenses/libheif-LICENSE
oiio_static_python-3.0.7.0.1.dist-info/licenses/licenses/libjpeg-LICENSE
oiio_static_python-3.0.7.0.1.dist-info/licenses/licenses/libjpegturbo-LICENSE
oiio_static_python-3.0.7.0.1.dist-info/licenses/licenses/libpng-LICENSE
oiio_static_python-3.0.7.0.1.dist-info/licenses/licenses/libtiff-LICENSE
oiio_static_python-3.0.7.0.1.dist-info/licenses/licenses/libwebp-LICENSE
oiio_static_python-3.0.7.0.1.dist-info/licenses/licenses/onetbb-LICENSE
oiio_static_python-3.0.7.0.1.dist-info/licenses/licenses/opencolorio-LICENSE
oiio_static_python-3.0.7.0.1.dist-info/licenses/licenses/openexr-LICENSE
oiio_static_python-3.0.7.0.1.dist-info/licenses/licenses/openimageio-LICENSE
oiio_static_python-3.0.7.0.1.dist-info/licenses/licenses/openjpeg-LICENSE
oiio_static_python-3.0.7.0.1.dist-info/licenses/licenses/ptex-LICENSE
oiio_static_python-3.0.7.0.1.dist-info/licenses/licenses/pybind11-LICENSE
oiio_static_python-3.0.7.0.1.dist-info/licenses/licenses/pystring-LICENSE
