Metadata-Version: 2.1
Name: oiio-static-python
Version: 3.0.7.0.1
Summary: Unofficial OpenImageIO Python wheels, including OpenColorIO
Home-page: https://github.com/pypoulp/oiio-python
Author: Paul Parneix
Keywords: OpenImageIO,OpenColorIO,image,processing,oiio,ocio,python,wrapper,binding,library
Classifier: Programming Language :: Python
Classifier: Programming Language :: Python :: 3
Classifier: Programming Language :: Python :: 3 :: Only
Classifier: Programming Language :: Python :: 3.8
Classifier: Programming Language :: Python :: 3.9
Classifier: Programming Language :: Python :: 3.10
Classifier: Programming Language :: Python :: 3.11
Classifier: Programming Language :: Python :: 3.12
Classifier: Programming Language :: Python :: 3.13
Classifier: Programming Language :: C++
Classifier: Programming Language :: Python :: Implementation :: CPython
Classifier: License :: OSI Approved :: Apache Software License
Classifier: License :: OSI Approved :: GNU General Public License v3 (GPLv3)
Requires-Python: >=3.8,<3.14
License-File: licenses/openexr-LICENSE
License-File: licenses/giflib-LICENSE
License-File: licenses/ptex-LICENSE
License-File: licenses/openimageio-LICENSE
License-File: licenses/hdf5-LICENSE
License-File: licenses/libjpeg-LICENSE
License-File: licenses/fmt-LICENSE
License-File: licenses/libwebp-LICENSE
License-File: licenses/pystring-LICENSE
License-File: licenses/imath-LICENSE
License-File: licenses/pybind11-LICENSE
License-File: licenses/libjpegturbo-LICENSE
License-File: licenses/libtiff-LICENSE
License-File: licenses/libheif-LICENSE
License-File: licenses/openjpeg-LICENSE
License-File: licenses/freetype-LICENSE
License-File: licenses/onetbb-LICENSE
License-File: licenses/libpng-LICENSE
License-File: licenses/opencolorio-LICENSE
License-File: LICENSE-GPL
Requires-Dist: numpy<2.3.0,>=1.21.2
Provides-Extra: dev
Requires-Dist: twine; extra == "dev"
Requires-Dist: black==24.2.0; extra == "dev"
Requires-Dist: isort==5.13.2; extra == "dev"
